whctools/__init__.py
whctools/aa3compat.py
whctools/admin.py
whctools/app_settings.py
whctools/apps.py
whctools/auth_hooks.py
whctools/forms.py
whctools/models.py
whctools/signals.py
whctools/tasks.py
whctools/urls.py
whctools/utils.py
whctools/views.py
whctools/migrations/0001_initial.py
whctools/migrations/0002_alter_applications_reject_reason.py
whctools/migrations/0003_aclhistory_reason_for_change.py
whctools/migrations/0004_alter_applications_reject_reason_applicationhistory.py
whctools/migrations/0005_alter_applicationhistory_options_acl_skill_plans.py
whctools/migrations/0006_rename_skill_plans_acl_skill_sets.py
whctools/migrations/0007_add_groups_to_acl.py
whctools/migrations/0008_allow_empty_acl_fields.py
whctools/migrations/0009_welcomemail.py
whctools/migrations/__init__.py
whctools/templates/whctools/base.html
whctools/templates/whctools/base_staff.html
whctools/templates/whctools/index.html
whctools/templates/whctools/list_acl_members.html
whctools/templates/whctools/staff/nav_pills.html
whctools/templates/whctools/staff/staff_apps_in_progress.html
whctools/templates/whctools/staff/staff_list_acls.html
whctools/templates/whctools/staff/staff_rejected_apps.html
whctools/tests/__init__.py
whctools/tests/test_tasks.py
whctools/views_actions/__init__.py
whctools/views_actions/player_actions.py
whctools/views_staff/__init__.py
whctools/views_staff/open_applications.py
whctools/views_staff/rejected_applications.py
whctools/views_staff/staff_utils.py
whctools-1.2.1.dist-info/licenses/LICENSE
whctools-1.2.1.dist-info/WHEEL
whctools-1.2.1.dist-info/METADATA
whctools-1.2.1.dist-info/RECORD
